kon/__init__.py
kon/model/__init__.py
kon/model/ctr_model/__init__.py
kon/model/ctr_model/layer/__init__.py
kon/model/ctr_model/layer/behavior_layer/__init__.py
kon/model/ctr_model/layer/behavior_layer/behavior_layer.py
kon/model/ctr_model/layer/behavior_layer/rnn_demo.py
kon/model/ctr_model/layer/core_layer/__init__.py
kon/model/ctr_model/layer/core_layer/core_layer.py
kon/model/ctr_model/layer/interactive_layer/__init__.py
kon/model/ctr_model/layer/interactive_layer/interactive_layer.py
kon/model/ctr_model/model/__init__.py
kon/model/ctr_model/model/models.py
kon/model/embedding/__init__.py
kon/model/embedding/model_test.py
kon/model/embedding/other/__init__.py
kon/model/embedding/other/other-collections.py
kon/model/embedding/other/other-networks.py
kon/model/embedding/setence_model/__init__.py
kon/model/embedding/setence_model/backone_language_model.py
kon/model/embedding/setence_model/backone_optimize.py
kon/model/embedding/setence_model/deepwalk.py
kon/model/embedding/setence_model/line.py
kon/model/embedding/setence_model/node2vec.py
kon/model/embedding/setence_model/sdne.py
kon/model/embedding/setence_model/walk_core_model.py
kon/model/embedding/util/__init__.py
kon/model/embedding/util/evaluate.py
kon/model/embedding/util/util_tool.py
kon/model/feature_eng/__init__.py
kon/model/feature_eng/base_model.py
kon/model/feature_eng/feature_transform.py
kon/utils/__init__.py
kon/utils/data_prepare.py
Data_Function-0.0.4.dist-info/LICENSE
Data_Function-0.0.4.dist-info/METADATA
Data_Function-0.0.4.dist-info/WHEEL
Data_Function-0.0.4.dist-info/top_level.txt
Data_Function-0.0.4.dist-info/RECORD
