Metadata-Version: 2.1
Name: Data-Function
Version: 0.0.4
Summary: kon
Home-page: https://github.com/TIXhjq/CTR_Function
Author: TIXhjq
Author-email: hjq1922451756@gmail.com
License: UNKNOWN
Platform: UNKNOWN
Classifier: Programming Language :: Python :: 3
Classifier: License :: OSI Approved :: Apache Software License
Requires-Python: >=3.6
